geoframepy/__init__.py
geoframepy/timeseries/__init__.py
geoframepy/timeseries/io_csv.py
geoframepy/whetgeo1d/__init__.py
geoframepy/whetgeo1d/grid_creator.py
geoframepy/whetgeo1d/grid_to_netcdf.py
geoframepy-0.0.5.dist-info/METADATA
geoframepy-0.0.5.dist-info/WHEEL
geoframepy-0.0.5.dist-info/top_level.txt
geoframepy-0.0.5.dist-info/RECORD
