Metadata-Version: 2.1
Name: geoframepy
Version: 0.0.5
Summary: A Python library for the GEOframe-NewAge system
Home-page: UNKNOWN
Author: Niccolò Tubini, Riccardo Rigon
Author-email: tubini.niccolo@gmail.com
License: UNKNOWN
Platform: UNKNOWN
Classifier: Programming Language :: Python :: 3
Classifier: License :: OSI Approved :: GNU General Public License v3 (GPLv3)
Classifier: Operating System :: OS Independent
Classifier: Development Status :: 5 - Production/Stable
Classifier: Intended Audience :: Science/Research
Requires-Python: >=3.6
